main.py
hn_news-0.1.0.dist-info/METADATA
hn_news-0.1.0.dist-info/WHEEL
hn_news-0.1.0.dist-info/entry_points.txt
hn_news-0.1.0.dist-info/top_level.txt
hn_news-0.1.0.dist-info/RECORD
