Metadata-Version: 2.4
Name: hn-news
Version: 0.1.0
Summary: Hacker News CLI client
Author-email: Mohannad Ahmed <mohnnadabdo21@gmail.com>
License: MIT
Requires-Python: >=3.12
Requires-Dist: httpx
Requires-Dist: beautifulsoup4
Requires-Dist: rich
